recsets/__init__.py
recsets/lastfm.py
recsets/utils.py
recsets-0.1.0.dist-info/METADATA
recsets-0.1.0.dist-info/WHEEL
recsets-0.1.0.dist-info/top_level.txt
recsets-0.1.0.dist-info/RECORD
